<?xml version='1.0' encoding='UTF-8'?>
<annotations><apprenant_id>1117</apprenant_id><pays>FR</pays><énoncé id="1"><STU>iszcze prosto na ulica niska </STU><POL>iść prosto ulicą niską</POL></énoncé><énoncé id="2"><STU>i obok spital  cienci na prawo </STU><POL>i obok szpitala w prawo</POL></énoncé><énoncé id="3"><STU>proszę iścz proce i proste proste proste</STU><POL>proszę iść prosto prosto prosto</POL></énoncé><énoncé id="4"><STU>i obok sklept</STU><POL>i obok sklepu</POL></énoncé><énoncé id="5"><STU>cz czrenczisz na lewo a na ulica dobra i an na lewo jest numer cztery </STU><POL>skręcisz w lewo w ulicę dobrą i na lewo jest numer cztery</POL></énoncé></annotations>