<?xml version='1.0' encoding='UTF-8'?>
<annotations><apprenant_id>4104</apprenant_id><pays>GE</pays><énoncé id="1"><STU>proszę idź prosto</STU><POL>proszę idź prosto</POL></énoncé><énoncé id="2"><STU>za szpita szpitalu proszę skręcać prawo</STU><POL>za szpitalem proszę skręcić w prawo</POL></énoncé><énoncé id="3"><STU>ulica nazywa się juli julicka slowackiego</STU><POL>ulica nazywa się juliusza słowackiego</POL></énoncé><énoncé id="4"><STU>proszę idź prosto i prosto  obek skole  i obek teatre  i obek slepu</STU><POL>proszę idź prosto i prosto obok szkoły i obok teatru i obok sklepu</POL></énoncé><énoncé id="5"><STU>i proszę skręcać na lewo</STU><POL>i proszę skręcić w lewo</POL></énoncé><énoncé id="6"><STU>ulica nazywa się dobra</STU><POL>ulica nazywa się dobra</POL></énoncé><énoncé id="7"><STU>i dom kowalski jest na lewo</STU><POL>i dom kowalskich jest na lewo</POL></énoncé></annotations>